scBridge/__init__.py
scBridge/bridge.py
scBridge/calculate_cluster.py
scBridge/data_processing.py
scBridge/draw_cluster.py
scBridge/logger.py
scBridge/model_component.py
scBridge/model_utlis.py
scBridge/split_datasets.py
scBridge/train_model.py
scBridge/version.py
scbridge-1.1.dist-info/licenses/LICENSE.txt
scbridge-1.1.dist-info/METADATA
scbridge-1.1.dist-info/WHEEL
scbridge-1.1.dist-info/top_level.txt
scbridge-1.1.dist-info/RECORD
